<?xml version = '1.0' encoding = 'UTF-8'?>
<TableProxyOraclev12c class="oracle.dbtools.crest.model.design.storage.oracle.v12c.TableProxyOraclev12c" name="PRICES" directorySegmentName="seg_0" id="56FE4CFE-AC46-C9A3-9213-86569747E69C">
<createdBy>On</createdBy>
<createdTime>2024-02-20 04:32:12 UTC</createdTime>
<ownerDesignName>design</ownerDesignName>
<schemaObject>8406AE37-98B7-2E42-DFB8-1D554E4273EA</schemaObject>
<logging>YES</logging>
<partitionedRowMovement>DISABLE</partitionedRowMovement>
<segment>C75E15B7-09E5-6BD4-95FB-6B25979DA544</segment>
<tableSpace>5FA16D2E-1B02-AA81-175A-9876AE2300B6</tableSpace>
<temporaryChanged>false</temporaryChanged>
<accessDriverType>oracle_loader</accessDriverType>
<rejectLimit></rejectLimit>
<inMemory>NO</inMemory>
<columnProxies itemClass="oracle.dbtools.crest.model.design.storage.oracle.v12c.ColumnProxyOraclev12c">
<ColumnProxy name="CREATEDAT" id="40D4C200-0C82-8E0C-AB50-C8597A97A6C7">
<createdBy>On</createdBy>
<createdTime>2024-02-20 04:32:12 UTC</createdTime>
<ownerDesignName>design</ownerDesignName>
</ColumnProxy>
<ColumnProxy name="order" id="45E9772C-51EC-4B7D-CE9B-221886CE34A2">
<createdBy>On</createdBy>
<createdTime>2024-02-20 04:32:12 UTC</createdTime>
<ownerDesignName>design</ownerDesignName>
<nameHasQuotes>true</nameHasQuotes>
</ColumnProxy>
<ColumnProxy name="ID" id="A2E8186C-9226-97B7-0A4C-0316B2E57D54">
<createdBy>On</createdBy>
<createdTime>2024-02-20 04:32:12 UTC</createdTime>
<ownerDesignName>design</ownerDesignName>
</ColumnProxy>
<ColumnProxy name="UPDATEDAT" id="A3811C08-3AB0-3CE1-3CF0-A550A92DA4D2">
<createdBy>On</createdBy>
<createdTime>2024-02-20 04:32:12 UTC</createdTime>
<ownerDesignName>design</ownerDesignName>
</ColumnProxy>
<ColumnProxy name="CODE" id="BEFF3AD7-AD83-FB46-B323-1DC1BEACA6A1">
<createdBy>On</createdBy>
<createdTime>2024-02-20 04:32:12 UTC</createdTime>
<ownerDesignName>design</ownerDesignName>
</ColumnProxy>
<ColumnProxy name="VALUE" id="EFD36279-05F1-22F4-2FC4-4CDE70729394">
<createdBy>On</createdBy>
<createdTime>2024-02-20 04:32:12 UTC</createdTime>
<ownerDesignName>design</ownerDesignName>
</ColumnProxy>
</columnProxies>
<primaryKeys>
<PrimaryKey class="oracle.dbtools.crest.model.design.storage.oracle.v10g.PKProxyOraclev10g" name="PRICES_PK" id="D3D3CF51-9755-8B8E-21E3-EAECC841F3D9">
<createdBy>On</createdBy>
<createdTime>2024-02-20 04:32:12 UTC</createdTime>
<ownerDesignName>design</ownerDesignName>
<schemaObject>8406AE37-98B7-2E42-DFB8-1D554E4273EA</schemaObject>
<segment>C851FE71-A2DC-2FBE-1FC7-C34B864EFA9B</segment>
<tableSpace>5FA16D2E-1B02-AA81-175A-9876AE2300B6</tableSpace>
<indexSegment>C851FE71-A2DC-2FBE-1FC7-C34B864EFA9B</indexSegment>
<indexSort>SORTED</indexSort>
<usingIndex>BY INDEX NAME</usingIndex>
</PrimaryKey>
</primaryKeys>
</TableProxyOraclev12c>